remofile/__init__.py
remofile/algorithm.py
remofile/cli.py
remofile/client.py
remofile/daemon.py
remofile/exceptions.py
remofile/keys.py
remofile/protocol.py
remofile/server.py
remofile/token.py
remofile/utils.py
remofile-1.0.0.dev6.dist-info/LICENSE.txt
remofile-1.0.0.dev6.dist-info/METADATA
remofile-1.0.0.dev6.dist-info/WHEEL
remofile-1.0.0.dev6.dist-info/entry_points.txt
remofile-1.0.0.dev6.dist-info/top_level.txt
remofile-1.0.0.dev6.dist-info/RECORD
