Metadata-Version: 2.1
Name: remofile
Version: 1.0.0.dev6
Summary: Quick and easy-to-use alternative to FTP
Home-page: https://www.sonkun-dev.net/project/remofile
Author: Jonathan De Wachter
Author-email: dewachter.jonathan@gmail.com
License: MIT
Project-URL: Documentation, http://remofile.readthedocs.io
Project-URL: Source, https://github.com/sonkun/remofile/
Project-URL: Tracker, https://github.com/sonkun/remofile/issues
Keywords: remofile file transfer ftp alternative quick embeddable secure protocol
Platform: UNKNOWN
Classifier: Development Status :: 4 - Beta
Classifier: Intended Audience :: Developers
Classifier: License :: OSI Approved :: MIT License
Classifier: Operating System :: OS Independent
Classifier: Programming Language :: Python :: 3
Classifier: Programming Language :: Python :: 3.6
Classifier: Programming Language :: Python :: 3.7
Classifier: Topic :: Communications :: File Sharing
Classifier: Topic :: Desktop Environment :: File Managers
Classifier: Topic :: Internet :: File Transfer Protocol (FTP)
Classifier: Topic :: System :: Filesystems
Requires-Python: >=3.6
Requires-Dist: Click
Requires-Dist: pyzmq
Requires-Dist: shortuuid
